setup.py
makosg/__init__.py
makosg/makosg.py
makosg/tests.py
makosg.egg-info/PKG-INFO
makosg.egg-info/SOURCES.txt
makosg.egg-info/dependency_links.txt
makosg.egg-info/requires.txt
makosg.egg-info/top_level.txt