Metadata-Version: 1.0
Name: makosg
Version: 0.0.3
Summary: Easily render rich html emails for sendgrid using mako templates
Home-page: https://github.com/bcajes/makosg/
Author: Brian Cajes
Author-email: brian.cajes@gmail.com
License: MIT License
Platform: UNKNOWN
